csle_ryu/__init__.py
csle_ryu/__version__.py
csle_ryu/constants/__init__.py
csle_ryu/constants/constants.py
csle_ryu/controllers/__init__.py
csle_ryu/controllers/learning_switch_controller.py
csle_ryu/controllers/learning_switch_stp_controller.py
csle_ryu/dao/__init__.py
csle_ryu/dao/agg_flow_statistic.py
csle_ryu/dao/avg_flow_statistic.py
csle_ryu/dao/avg_port_statistic.py
csle_ryu/dao/flow_statistic.py
csle_ryu/dao/port_statistic.py
csle_ryu/dao/ryu_controller_type.py
csle_ryu/monitor/__init__.py
csle_ryu/monitor/flow_and_port_stats_monitor.py
csle_ryu-0.9.45.dist-info/METADATA
csle_ryu-0.9.45.dist-info/WHEEL
csle_ryu-0.9.45.dist-info/top_level.txt
csle_ryu-0.9.45.dist-info/RECORD
